Workbook

Sheet Customer Details
A1: Customer ID | B1: Customer Name | C1: Phone Number | D1: Email | E1: Address | F1: Registration Date
A2: CUST001 | B2: Aarav Sharma | C2: 9786579303 | D2: aarav.sharma@example.com | E2: 29 MG Road, Hyderabad | F2: 45390
A3: CUST002 | B3: Vivaan Verma | C3: 9249827706 | D3: vivaan.verma@example.com | E3: 189 MG Road, Bengaluru | F3: 45579
A4: CUST003 | B4: Aditi Iyer | C4: 9134126396 | D4: aditi.iyer@example.com | E4: 8 MG Road, Delhi | F4: 45399
A5: CUST004 | B5: Diya Patel | C5: 9746412689 | D5: diya.patel@example.com | E5: 7 Church Street, Delhi | F5: 45647
A6: CUST005 | B6: Kabir Nair | C6: 9853041955 | D6: kabir.nair@example.com | E6: 140 Brigade Road, Delhi | F6: 45523
A7: CUST006 | B7: Isha Gupta | C7: 9398704996 | D7: isha.gupta@example.com | E7: 2 Anna Salai, Kolkata | F7: 45452
A8: CUST007 | B8: Rohan Reddy | C8: 9266944844 | D8: rohan.reddy@example.com | E8: 56 Park Street, Bengaluru | F8: 45335
A9: CUST008 | B9: Meera Menon | C9: 9203848421 | D9: meera.menon@example.com | E9: 92 Park Street, Hyderabad | F9: 45315
A10: CUST009 | B10: Arjun Singh | C10: 9593303705 | D10: arjun.singh@example.com | E10: 138 MG Road, Kolkata | F10: 45340
A11: CUST010 | B11: Sanya Rao | C11: 9414797776 | D11: sanya.rao@example.com | E11: 161 Church Street, Pune | F11: 45572
A12: CUST011 | B12: Kunal Kapoor | C12: 9856528252 | D12: kunal.kapoor@example.com | E12: 18 MG Road, Delhi | F12: 45415
A13: CUST012 | B13: Priya Das | C13: 9349957310 | D13: priya.das@example.com | E13: 26 Brigade Road, Hyderabad | F13: 45525
... A16: CUST015 | B16: Sara Pillai | C16: 9362863730 | D16: sara.pillai@example.com | E16: 42 Brigade Road, Kolkata | F16: 45433

Sheet Sheet1
K16: #VALUE!

Sheet Food Menu
A1: Food ID | B1: Food Name | C1: Category | D1: Description | E1: Price | F1: Availability | G1: Preparation Time (mins) | H1: Total Qty Sold | I1: Total Revenue (excl. Cancelled)
A2: FOOD001 | B2: Paneer Tikka | C2: Starters | D2: Grilled cottage cheese marinated in spices | E2: rps220 | F2: Available | G2: 15 | H2: =SUMIFS(Orders!$G$2:$G$11,Orders!$E$2:$E$11,A2,Orders!$L$2:$L$11,"<>Cancelled") -> 1 | I2: =SUMIFS(Orders!$I$2:$I$11,Orders!$E$2:$E$11,A2,Orders!$L$2:$L$11,"<>Cancelled") -> #VALUE!
A3: FOOD002 | B3: Chicken 65 | C3: Starters | D3: Spicy deep-fried chicken bites | E3: 260 | F3: Available | G3: 18 | H3: =SUMIFS(Orders!$G$2:$G$11,Orders!$E$2:$E$11,A3,Orders!$L$2:$L$11,"<>Cancelled") -> 4 | I3: =SUMIFS(Orders!$I$2:$I$11,Orders!$E$2:$E$11,A3,Orders!$L$2:$L$11,"<>Cancelled") -> 1040
A4: FOOD003 | B4: Veg Spring Rolls | C4: Starters | D4: Crispy rolls stuffed with vegetables | E4: 180 | F4: Available | G4: 12 | H4: =SUMIFS(Orders!$G$2:$G$11,Orders!$E$2:$E$11,A4,Orders!$L$2:$L$11,"<>Cancelled") -> 0 | I4: =SUMIFS(Orders!$I$2:$I$11,Orders!$E$2:$E$11,A4,Orders!$L$2:$L$11,"<>Cancelled") -> 0
A5: FOOD004 | B5: Butter Chicken | C5: Main Course | D5: Creamy tomato based chicken curry | E5: 380 | F5: Available | G5: 25 | H5: =SUMIFS(Orders!$G$2:$G$11,Orders!$E$2:$E$11,A5,Orders!$L$2:$L$11,"<>Cancelled") -> 0 | I5: =SUMIFS(Orders!$I$2:$I$11,Orders!$E$2:$E$11,A5,Orders!$L$2:$L$11,"<>Cancelled") -> 0
A6: FOOD005 | B6: Paneer Butter Masala | C6: Main Course | D6: Cottage cheese in rich tomato gravy | E6: 340 | F6: Available | G6: 22 | H6: =SUMIFS(Orders!$G$2:$G$11,Orders!$E$2:$E$11,A6,Orders!$L$2:$L$11,"<>Cancelled") -> 2 | I6: =SUMIFS(Orders!$I$2:$I$11,Orders!$E$2:$E$11,A6,Orders!$L$2:$L$11,"<>Cancelled") -> 680
A7: FOOD006 | B7: Veg Biryani | C7: Main Course | D7: Fragrant rice cooked with mixed vegetables | E7: 300 | F7: Available | G7: 30 | H7: =SUMIFS(Orders!$G$2:$G$11,Orders!$E$2:$E$11,A7,Orders!$L$2:$L$11,"<>Cancelled") -> 0 | I7: =SUMIFS(Orders!$I$2:$I$11,Orders!$E$2:$E$11,A7,Orders!$L$2:$L$11,"<>Cancelled") -> 0
A8: FOOD007 | B8: Chicken Biryani | C8: Main Course | D8: Fragrant rice layered with spiced chicken | E8: 350 | F8: Unavailable | G8: 30 | H8: =SUMIFS(Orders!$G$2:$G$11,Orders!$E$2:$E$11,A8,Orders!$L$2:$L$11,"<>Cancelled") -> 0 | I8: =SUMIFS(Orders!$I$2:$I$11,Orders!$E$2:$E$11,A8,Orders!$L$2:$L$11,"<>Cancelled") -> 0
A9: FOOD008 | B9: Gulab Jamun | C9: Desserts | D9: Deep fried milk balls soaked in sugar syrup | E9: 120 | F9: Available | G9: 10 | H9: =SUMIFS(Orders!$G$2:$G$11,Orders!$E$2:$E$11,A9,Orders!$L$2:$L$11,"<>Cancelled") -> 0 | I9: =SUMIFS(Orders!$I$2:$I$11,Orders!$E$2:$E$11,A9,Orders!$L$2:$L$11,"<>Cancelled") -> 0
A10: FOOD009 | B10: Chocolate Brownie | C10: Desserts | D10: Warm brownie served with chocolate sauce | E10: 160 | F10: Available | G10: 12 | H10: =SUMIFS(Orders!$G$2:$G$11,Orders!$E$2:$E$11,A10,Orders!$L$2:$L$11,"<>Cancelled") -> 0 | I10: =SUMIFS(Orders!$I$2:$I$11,Orders!$E$2:$E$11,A10,Orders!$L$2:$L$11,"<>Cancelled") -> 0
A11: FOOD010 | B11: Ice Cream Sundae | C11: Desserts | D11: Assorted ice cream with toppings | E11: 150 | F11: Available | G11: 12 | H11: 1 | I11: $150.00

Sheet Restaurant Details
A1: Restaurant ID | B1: Restaurant Name | C1: Owner Name | D1: Contact Number | E1: Email | F1: Address | G1: Cuisine Type | H1: Opening Time | I1: Closing Time | J1: Restaurant Status
A2: REST001 | B2: Spice Garden | C2: Ramesh Kumar | D2: 9876543210 | E2: contact@spicegarden.com | F2: 12 MG Road, Chennai | G2: Indian | H2: 0.41666667 | I2: 0.95833333 | J2: Open
A3: REST002 | B3: Tandoori Flames | C3: Sunita Rao | D3: 9876543211 | E3: info@tandooriflames.com | F3: 45 Brigade Road, Bengaluru | G3: North Indian | H3: 0.45833333 | I3: 0.9375 | J3: Open
A4: REST003 | B4: Sweet Treats Bakery | C4: Anil Mehta | D4: 9876543212 | E4: hello@sweettreats.com | F4: 8 Park Street, Kolkata | G4: Bakery & Desserts | H4: 0.375 | I4: 0.875 | J4: Open
A5: REST004 | B5: Cafe Brew | C5: Farhan Ali | D5: 9876543213 | E5: support@cafebrew.com | F5: 22 Church Street, Bengaluru | G5: Cafe | H5: 0.33333333 | I5: 0.91666667 | J5: Closed
A6: REST005 | B6: Quick Bites | C6: Lakshmi Narayan | D6: 9876543214 | E6: care@quickbites.com | F6: 3 Anna Salai, Chennai | G6: Fast Food | H6: 0.41666667 | I6: 0.97916667 | J6: Open

Sheet Orders
A1: Order ID | B1: Customer ID | C1: Customer Name | D1: Order Date | E1: Food ID | F1: Food Name | G1: Quantity | H1: Unit Price | I1: Total Amount | J1: Payment Method | K1: Payment Status | L1: Order Status
A2: ORD0001 | B2: ='Customer Details'!A4 -> CUST003 | C2: ='Customer Details'!B4 -> Aditi Iyer | D2: 45771 | E2: ='Food Menu'!A6 -> FOOD005 | F2: ='Food Menu'!B6 -> Paneer Butter Masala | G2: 2 | H2: ='Food Menu'!E6 -> 340 | I2: =G2*H2 -> 680 | J2: Wallet | K2: Paid | L2: Delivered
A3: ORD0002 | B3: ='Customer Details'!A13 -> CUST012 | C3: ='Customer Details'!B13 -> Priya Das | D3: 45850 | E3: ='Food Menu'!A11 -> FOOD010 | F3: ='Food Menu'!B11 -> Ice Cream Sundae | G3: 4 | H3: ='Food Menu'!E11 -> 150 | I3: =G3*H3 -> 600 | J3: Credit Card | K3: Pending | L3: Cancelled
A4: ORD0003 | B4: ='Customer Details'!A9 -> CUST008 | C4: ='Customer Details'!B9 -> Meera Menon | D4: 45693 | E4: ='Food Menu'!A3 -> FOOD002 | F4: ='Food Menu'!B3 -> Chicken 65 | G4: 1 | H4: ='Food Menu'!E3 -> 260 | I4: =G4*H4 -> 260 | J4: Credit Card | K4: Paid | L4: Delivered
A5: ORD0004 | B5: ='Customer Details'!A8 -> CUST007 | C5: ='Customer Details'!B8 -> Rohan Reddy | D5: 45851 | E5: ='Food Menu'!A11 -> FOOD010 | F5: ='Food Menu'!B11 -> Ice Cream Sundae | G5: 1 | H5: ='Food Menu'!E11 -> 150 | I5: =G5*H5 -> 150 | J5: Wallet | K5: Pending | L5: Cancelled
A6: ORD0005 | B6: ='Customer Details'!A15 -> CUST014 | C6: ='Customer Details'!B15 -> Rahul Chatterjee | D6: 45925 | E6: ='Food Menu'!A2 -> FOOD001 | F6: ='Food Menu'!B2 -> Paneer Tikka | G6: 1 | H6: ='Food Menu'!E2 -> rps220 | I6: =G6*H6 -> #VALUE! | J6: Debit Card | K6: Paid | L6: Delivered
A7: ORD0006 | B7: ='Customer Details'!A7 -> CUST006 | C7: ='Customer Details'!B7 -> Isha Gupta | D7: 45844 | E7: ='Food Menu'!A3 -> FOOD002 | F7: ='Food Menu'!B3 -> Chicken 65 | G7: 3 | H7: ='Food Menu'!E3 -> 260 | I7: =G7*H7 -> 780 | J7: UPI | K7: Failed | L7: Pending
A8: ORD0007 | B8: ='Customer Details'!A10 -> CUST009 | C8: ='Customer Details'!B10 -> Arjun Singh | D8: 45904 | E8: ='Food Menu'!#REF! -> #REF! | F8: ='Food Menu'!#REF! -> #REF! | G8: 2 | H8: ='Food Menu'!#REF! -> #REF! | I8: =G8*H8 -> #REF! | J8: Debit Card | K8: Paid | L8: Delivered
A9: ORD0008 | B9: ='Customer Details'!A10 -> CUST009 | C9: ='Customer Details'!B10 -> Arjun Singh | D9: 45728 | E9: ='Food Menu'!A11 -> FOOD010 | F9: ='Food Menu'!B11 -> Ice Cream Sundae | G9: 2 | H9: ='Food Menu'!E11 -> 150 | I9: =G9*H9 -> 300 | J9: Credit Card | K9: Paid | L9: Delivered
A10: ORD0009 | B10: ='Customer Details'!A14 -> CUST013 | C10: ='Customer Details'!B14 -> Neha Bose | D10: 45824 | E10: ='Food Menu'!#REF! -> #REF! | F10: ='Food Menu'!#REF! -> #REF! | G10: 1 | H10: ='Food Menu'!#REF! -> #REF! | I10: =G10*H10 -> #REF! | J10: Cash on Delivery | K10: Failed | L10: Confirmed
A11: ORD0010 | B11: ='Customer Details'!A16 -> CUST015 | C11: ='Customer Details'!B16 -> Sara Pillai | D11: 45749 | E11: ='Food Menu'!#REF! -> #REF! | F11: ='Food Menu'!#REF! -> #REF! | G11: 3 | H11: ='Food Menu'!#REF! -> #REF! | I11: =G11*H11 -> #REF! | J11: Credit Card | K11: Refunded | L11: Cancelled

Sheet Delivery Details
A1: Delivery ID | B1: Order ID | C1: Delivery Partner ID | D1: Delivery Partner Name | E1: Contact Number | F1: Pickup Time | G1: Delivery Time | H1: Delivery Status
A2: DEL0001 | B2: =Orders!A2 -> ORD0001 | C2: DP001 | D2: Suresh Yadav | E2: 9123456780 | F2: 45771.448 | G2: 45771.475 | H2: Delivered
A3: DEL0002 | B3: =Orders!A4 -> ORD0003 | C3: DP005 | D3: Vikram Joshi | E3: 9123456784 | F3: 45693.458 | G3: 45693.484 | H3: Delivered
A4: DEL0003 | B4: =Orders!A6 -> ORD0005 | C4: DP002 | D4: Ravi Teja | E4: 9123456781 | F4: 45925.771 | G4: 45925.787 | H4: Delivered
A5: DEL0004 | B5: =Orders!A8 -> ORD0007 | C5: DP003 | D5: Manoj Kumar | E5: 9123456782 | F5: 45904.469 | G5: 45904.49 | H5: Delivered
A6: DEL0005 | B6: =Orders!A9 -> ORD0008 | C6: DP003 | D6: Manoj Kumar | E6: 9123456782 | F6: 45728.531 | G6: 45728.563 | H6: Delivered
A7: DEL0006 | B7: =Orders!#REF! -> #REF! | C7: DP005 | D7: Vikram Joshi | E7: 9123456784 | F7: 45928.583 | G7: 45928.612 | H7: Delivered
A8: DEL0007 | B8: =Orders!#REF! -> #REF! | C8: DP005 | D8: Vikram Joshi | E8: 9123456784 | F8: 45790.583 | G8: 45790.618 | H8: Delivered
A9: DEL0008 | B9: =Orders!#REF! -> #REF! | C9: DP002 | D9: Ravi Teja | E9: 9123456781 | F9: 45755.583 | H9: In Transit
A10: DEL0009 | B10: =Orders!#REF! -> #REF! | C10: DP001 | D10: Suresh Yadav | E10: 9123456780 | F10: 45908.76 | G10: 45908.78 | H10: Delivered
A11: DEL0010 | B11: =Orders!#REF! -> #REF! | C11: DP003 | D11: Manoj Kumar | E11: 9123456782 | F11: 45877.802 | G11: 45877.831 | H11: Delivered

Sheet Payment Details
A1: Payment ID | B1: Order ID | C1: Customer ID | D1: Payment Date | E1: Amount | F1: Payment Method | G1: Transaction ID | H1: Payment Status
A2: PAY0001 | B2: =Orders!A2 -> ORD0001 | C2: =Orders!B2 -> CUST003 | D2: =Orders!D2 -> 45771 | E2: =Orders!I2 -> 680 | F2: =Orders!J2 -> Wallet | G2: TXN487151 | H2: =Orders!K2 -> Paid
A3: PAY0002 | B3: =Orders!A3 -> ORD0002 | C3: =Orders!B3 -> CUST012 | D3: =Orders!D3 -> 45850 | E3: =Orders!I3 -> 600 | F3: =Orders!J3 -> Credit Card | G3: TXN710805 | H3: =Orders!K3 -> Pending
A4: PAY0003 | B4: =Orders!A4 -> ORD0003 | C4: =Orders!B4 -> CUST008 | D4: =Orders!D4 -> 45693 | E4: =Orders!I4 -> 260 | F4: =Orders!J4 -> Credit Card | G4: TXN679364 | H4: =Orders!K4 -> Paid
A5: PAY0004 | B5: =Orders!A5 -> ORD0004 | C5: =Orders!B5 -> CUST007 | D5: =Orders!D5 -> 45851 | E5: =Orders!I5 -> 150 | F5: =Orders!J5 -> Wallet | G5: TXN255287 | H5: =Orders!K5 -> Pending
A6: PAY0005 | B6: =Orders!A6 -> ORD0005 | C6: =Orders!B6 -> CUST014 | D6: =Orders!D6 -> 45925 | E6: =Orders!I6 -> #VALUE! | F6: =Orders!J6 -> Debit Card | G6: TXN550664 | H6: =Orders!K6 -> Paid
A7: PAY0006 | B7: =Orders!A7 -> ORD0006 | C7: =Orders!B7 -> CUST006 | D7: =Orders!D7 -> 45844 | E7: =Orders!I7 -> 780 | F7: =Orders!J7 -> UPI | G7: TXN233636 | H7: =Orders!K7 -> Failed
A8: PAY0007 | B8: =Orders!A8 -> ORD0007 | C8: =Orders!B8 -> CUST009 | D8: =Orders!D8 -> 45904 | E8: =Orders!I8 -> #REF! | F8: =Orders!J8 -> Debit Card | G8: TXN143860 | H8: =Orders!K8 -> Paid
A9: PAY0008 | B9: =Orders!A9 -> ORD0008 | C9: =Orders!B9 -> CUST009 | D9: =Orders!D9 -> 45728 | E9: =Orders!I9 -> 300 | F9: =Orders!J9 -> Credit Card | G9: TXN423232 | H9: =Orders!K9 -> Paid
A10: PAY0009 | B10: =Orders!A10 -> ORD0009 | C10: =Orders!B10 -> CUST013 | D10: =Orders!D10 -> 45824 | E10: =Orders!I10 -> #REF! | F10: =Orders!J10 -> Cash on Delivery | G10: TXN482364 | H10: =Orders!K10 -> Failed

Sheet Reports & Dashboard
A1: Food Delivery Management — Reports & Dashboard
A2: Live figures calculated from Customer, Food, Orders, Delivery & Payment sheets
A4: Total Customers | C4: Total Orders | E4: Total Revenue | G4: Pending Orders
A5: =COUNTA('Customer Details'!A2:A16) -> 15 | C5: =COUNTA(Orders!A2:A11) -> 10 | E5: =SUMIFS(Orders!I2:I11,Orders!L2:L11,"<>Cancelled") -> #VALUE! | G5: =COUNTIF(Orders!L2:L11,"Pending") -> 1
A8: Completed Orders | C8: Cancelled Orders | E8: Average Order Value
A9: =COUNTIF(Orders!L2:L11,"Delivered") -> 5 | C9: =COUNTIF(Orders!L2:L11,"Cancelled") -> 3 | E9: =IFERROR(SUMIFS(Orders!I2:I11,Orders!L2:L11,"<>Cancelled")/COUNTIFS(Orders!L2:L11,"<>Cancelled"),0) -> 0
A12: Most Popular Food Item | E12: Top-Selling Food Category
A13: =IFERROR(INDEX('Food Menu'!$B$2:$B$11,MATCH(MAX('Food Menu'!$H$2:$H$11),'Food Menu'!$H$2:$H$11,0)),"N/A") -> Chicken 65 | E13: =INDEX(A19:A23,MATCH(MAX(B19:B23),B19:B23,0)) -> #VALUE!
A17: Category Revenue Breakdown (excl. Cancelled orders)
A18: Category | B18: Total Revenue
A19: Starters | B19: =SUMIFS('Food Menu'!$I$2:$I$11,'Food Menu'!$C$2:$C$11,A19) -> #VALUE!
A20: Main Course | B20: =SUMIFS('Food Menu'!$I$2:$I$11,'Food Menu'!$C$2:$C$11,A20) -> 680
A21: Desserts | B21: =SUMIFS('Food Menu'!$I$2:$I$11,'Food Menu'!$C$2:$C$11,A21) -> 0
A22: Beverages | B22: =SUMIFS('Food Menu'!$I$2:$I$11,'Food Menu'!$C$2:$C$11,A22) -> 0
A23: Snacks | B23: =SUMIFS('Food Menu'!$I$2:$I$11,'Food Menu'!$C$2:$C$11,A23) -> 0
A26: Order Status Breakdown
A27: Order Status | B27: Count
A28: Pending | B28: =COUNTIF(Orders!$L$2:$L$11,A28) -> 1
A29: Confirmed | B29: =COUNTIF(Orders!$L$2:$L$11,A29) -> 1
A30: Preparing | B30: =COUNTIF(Orders!$L$2:$L$11,A30) -> 0
A31: Out for Delivery | B31: =COUNTIF(Orders!$L$2:$L$11,A31) -> 0
A32: Delivered | B32: =COUNTIF(Orders!$L$2:$L$11,A32) -> 5
A33: Cancelled | B33: =COUNTIF(Orders!$L$2:$L$11,A33) -> 3
A53: Monthly Revenue Trend (2025)
A54: Month | B54: Revenue
A55: Jan | B55: =SUMPRODUCT((MONTH(Orders!$D$2:$D$11)=1)*(Orders!$L$2:$L$11<>"Cancelled")*Orders!$I$2:$I$11) -> #VALUE!
A56: Feb | B56: =SUMPRODUCT((MONTH(Orders!$D$2:$D$11)=2)*(Orders!$L$2:$L$11<>"Cancelled")*Orders!$I$2:$I$11) -> #VALUE!
A57: Mar | B57: =SUMPRODUCT((MONTH(Orders!$D$2:$D$11)=3)*(Orders!$L$2:$L$11<>"Cancelled")*Orders!$I$2:$I$11) -> #VALUE!
A58: Apr | B58: =SUMPRODUCT((MONTH(Orders!$D$2:$D$11)=4)*(Orders!$L$2:$L$11<>"Cancelled")*Orders!$I$2:$I$11) -> #VALUE!
A59: May | B59: =SUMPRODUCT((MONTH(Orders!$D$2:$D$11)=5)*(Orders!$L$2:$L$11<>"Cancelled")*Orders!$I$2:$I$11) -> #VALUE!
A60: Jun | B60: =SUMPRODUCT((MONTH(Orders!$D$2:$D$11)=6)*(Orders!$L$2:$L$11<>"Cancelled")*Orders!$I$2:$I$11) -> #VALUE!
A61: Jul | B61: =SUMPRODUCT((MONTH(Orders!$D$2:$D$11)=7)*(Orders!$L$2:$L$11<>"Cancelled")*Orders!$I$2:$I$11) -> #VALUE!
A62: Aug | B62: =SUMPRODUCT((MONTH(Orders!$D$2:$D$11)=8)*(Orders!$L$2:$L$11<>"Cancelled")*Orders!$I$2:$I$11) -> #VALUE!
A63: Sep | B63: =SUMPRODUCT((MONTH(Orders!$D$2:$D$11)=9)*(Orders!$L$2:$L$11<>"Cancelled")*Orders!$I$2:$I$11) -> #VALUE!
A64: Oct | B64: =SUMPRODUCT((MONTH(Orders!$D$2:$D$11)=10)*(Orders!$L$2:$L$11<>"Cancelled")*Orders!$I$2:$I$11) -> #VALUE!
A65: Nov | B65: =SUMPRODUCT((MONTH(Orders!$D$2:$D$11)=11)*(Orders!$L$2:$L$11<>"Cancelled")*Orders!$I$2:$I$11) -> #VALUE!
A66: Dec | B66: =SUMPRODUCT((MONTH(Orders!$D$2:$D$11)=12)*(Orders!$L$2:$L$11<>"Cancelled")*Orders!$I$2:$I$11) -> #VALUE!

Sheet a
